stream_rpc/__init__.py
stream_rpc/common.py
stream_rpc/crypto.py
stream_rpc-0.0.1.dist-info/LICENSE
stream_rpc-0.0.1.dist-info/METADATA
stream_rpc-0.0.1.dist-info/WHEEL
stream_rpc-0.0.1.dist-info/top_level.txt
stream_rpc-0.0.1.dist-info/RECORD
